Metadata-Version: 1.1
Name: django-cgi-wrap
Version: 0.2.0
Summary: Wrapper to integrate CGI scripts into django views.
Home-page: https://github.com/nmandery/django_cgi_wrap
Author: Nico Mandery
Author-email: nico@nmandery.net
License: MIT
Platform: UNKNOWN
Classifier: Programming Language :: Python :: 2
Classifier: Programming Language :: Python :: 3
Classifier: Intended Audience :: Developers
Classifier: License :: OSI Approved :: MIT License
Classifier: Topic :: Software Development :: Libraries
